{
	"name": "PlayAgain",
	"plugin-id": "Sprite",
	"sid": 979514643147880,
	"isGlobal": false,
	"instanceVariables": [],
	"behaviorTypes": [
		{
			"behaviorId": "Sin",
			"name": "Sine",
			"sid": 551580589024644
		}
	],
	"effectTypes": [],
	"animations": {
		"items": [
			{
				"frames": [
					{
						"width": 578,
						"height": 219,
						"originX": 0.5,
						"originY": 0.5,
						"originalSource": "",
						"exportFormat": "png",
						"exportQuality": 0.8,
						"imageSpriteId": 33,
						"useCollisionPoly": true,
						"duration": 1
					}
				],
				"sid": 890453041923666,
				"name": "Default",
				"isLooping": false,
				"isPingPong": false,
				"repeatCount": 1,
				"repeatTo": 0,
				"speed": 5
			}
		],
		"subfolders": []
	}
}